garytale/__init__.py
garytale/main.py
garytale-0.1.3.dist-info/LICENSE
garytale-0.1.3.dist-info/METADATA
garytale-0.1.3.dist-info/WHEEL
garytale-0.1.3.dist-info/RECORD
