Metadata-Version: 2.3
Name: garytale
Version: 0.1.3
Summary: Library for working with Aglient Cary 60 kinetics scan measurements with simultaneous irradiation, as seen in the working group under Prof. Wöll (IPC RWTH Aachen).
License: MIT
Author: Filip Vukelić
Author-email: filip.vukelic@rwth-aachen.de
Requires-Python: >=3.11
Classifier: License :: OSI Approved :: MIT License
Classifier: Programming Language :: Python :: 3
Classifier: Programming Language :: Python :: 3.11
Classifier: Programming Language :: Python :: 3.12
Classifier: Programming Language :: Python :: 3.13
Requires-Dist: matplotlib (>=3.10.0,<4.0.0)
Requires-Dist: numpy (>=2.2.2,<3.0.0)
Requires-Dist: pandas (>=2.2.3,<3.0.0)
Project-URL: Repository, https://github.com/filvuk/garytale
